apiclient/__init__.py
apiclient/core.py
apiclient/methods.py
instant_api_client-0.1.2.dist-info/LICENSE
instant_api_client-0.1.2.dist-info/METADATA
instant_api_client-0.1.2.dist-info/WHEEL
instant_api_client-0.1.2.dist-info/top_level.txt
instant_api_client-0.1.2.dist-info/RECORD
