Metadata-Version: 2.1
Name: instant-api-client
Version: 0.1.2
Summary: Create API wrappers/clients in minutes, enjoying both blocking and async interfaces from one codebase!
Home-page: https://github.com/FalseDev/instant-api-client
Author: FalseDev
License: MIT
Platform: UNKNOWN
Classifier: Programming Language :: Python :: 3
Classifier: Intended Audience :: Developers
Classifier: License :: OSI Approved :: MIT License
Classifier: Operating System :: OS Independent
Classifier: Topic :: Internet
Classifier: Topic :: Software Development :: Libraries
Classifier: Topic :: Software Development :: Libraries :: Python Modules
Classifier: Topic :: Utilities
Requires-Python: >=3.6
